novigo/__init__.py
novigo/models/trained_model.sav
novigo-0.0.12.dist-info/METADATA
novigo-0.0.12.dist-info/RECORD
novigo-0.0.12.dist-info/WHEEL
novigo-0.0.12.dist-info/top_level.txt
